Metadata-Version: 1.0
Name: dnatools
Version: 0.1
Summary: Functions for working with DNA sequences
Home-page: http://pythonforbiologists.com
Author: Martin Jones
Author-email: martin@pythonforbiologists.com
License: MIT
Platform: UNKNOWN
